{"is_source_file": false, "format": "", "description": "", "external_files": [], "external_methods": [], "published": [], "classes": [], "methods": [], "calls": [], "search-terms": [], "state": 2, "file_id": 30, "knowledge_revision": 68, "git_revision": "df00464c1c27765d95f642c9c13429e643ca7b39", "hash": "ecaf29ae072beb8364fa679d353950e6", "format-version": 4, "code-base-name": "android_frontend", "filename": "android_frontend/README.md", "revision_history": [{"68": "df00464c1c27765d95f642c9c13429e643ca7b39"}]}